dropwise_metrics/__init__.py
dropwise_metrics/base.py
dropwise_metrics/metrics/__init__.py
dropwise_metrics/metrics/entropy.py
dropwise_metrics/tasks/__init__.py
dropwise_metrics/tasks/question_answering.py
dropwise_metrics/tasks/regression.py
dropwise_metrics/tasks/sequence_classification.py
dropwise_metrics/tasks/token_classification.py
dropwise_metrics-0.1.0.dist-info/METADATA
dropwise_metrics-0.1.0.dist-info/WHEEL
dropwise_metrics-0.1.0.dist-info/top_level.txt
dropwise_metrics-0.1.0.dist-info/RECORD
