Metadata-Version: 2.1
Name: dropwise-metrics
Version: 0.1.0
Summary: TorchMetrics-compatible predictive uncertainty metrics using MC Dropout
Home-page: https://github.com/aryanator/dropwise-metrics
Author: Aryan Patil
Author-email: aryanator01@gmail.com
Classifier: Programming Language :: Python :: 3
Classifier: License :: OSI Approved :: MIT License
Classifier: Operating System :: OS Independent
Requires-Python: >=3.7
Requires-Dist: torch
Requires-Dist: torchmetrics
Requires-Dist: transformers
